extention/customUnit.v
module custom_backprop_unit (
    input  wire                 clk,          // System Clock
    input  wire                 rst_n,        // Active-low Reset
    input  wire                 enable,       // Optional: Only update when instruction is valid
    
    // Inputs from Register File / Memory
    input  wire signed [31:0]   error_term,   // Input 1 (Calculated Error)
    input  wire signed [31:0]   gradient_val, // Input 2 (From Surrogate RAM)

    // Output to Pipeline/ALU
    output reg  signed [31:0]   delta_out     // The calculated gradient change
);

    // --- 1. Internal Signals (Combinational Math) ---
    wire signed [31:0] error_scaled;
    wire signed [63:0] raw_product;
    wire signed [63:0] shifted_result;

    // --- 2. Step A: Pre-Scaling (Matches your Diagram bubble "(Error_term)>>2") ---
    // We use arithmetic shift (>>>) to preserve the sign of the error.
    assign error_scaled = error_term >>> 2;

    // --- 3. Step B: Multiplication (Matches "Multiplier" box) ---
    // 32-bit * 32-bit = 64-bit result to prevent overflow.
    assign raw_product = error_scaled * gradient_val;

    // --- 4. Step C: Post-Scaling (Matches "Shift Right 8" box) ---
    // Fixed-point adjustment (division by 256).
    assign shifted_result = raw_product >>> 8;

    // --- 5. Step D: Pipeline Register ---
    // This holds the value for the NEXT clock cycle, allowing the 
    // Weight Update (Addition) to happen in cycle 2.
    always @(posedge clk or negedge rst_n) begin
        if (!rst_n) begin
            delta_out <= 32'd0;
        end else if (enable) begin
            // Truncate back to 32 bits and store in the register
            delta_out <= shifted_result[31:0];
        end
    end

endmodule

RISC_V/extention/customUnit_tb.v
`timescale 1ns / 1ps

module custom_backprop_unit_tb;

    // --- 1. Signal Declarations ---
    reg         clk;
    reg         rst_n;
    reg         enable;
    reg  signed [31:0] error_term;
    reg  signed [31:0] gradient_val;
    wire signed [31:0] delta_out;

    // --- 2. Instantiate the Unit Under Test (UUT) ---
    custom_backprop_unit uut (
        .clk(clk),
        .rst_n(rst_n),
        .enable(enable),
        .error_term(error_term),
        .gradient_val(gradient_val),
        .delta_out(delta_out)
    );

    // --- 3. Clock Generation (10ns period = 100MHz) ---
    always #5 clk = ~clk;

    // --- 4. Stimulus Block ---
    initial begin
        // Initialize Signals
        clk = 0;
        rst_n = 0;
        enable = 0;
        error_term = 0;
        gradient_val = 0;

        // Setup GTKWave Dumping
        $dumpfile("backprop_sim.vcd");
        $dumpvars(0, custom_backprop_unit_tb);

        // Reset Sequence
        #20 rst_n = 1;
        #10 enable = 1;

        // Test Case 1: Simple Positive Values
        // (1024 >> 2) * 256 >> 8  =>  256 * 256 >> 8 = 256
        error_term = 32'd1024; 
        gradient_val = 32'd256;
        #10; 
        $display("Time: %t | Error: %d | Grad: %d | Delta: %d", $time, error_term, gradient_val, delta_out);

        // Test Case 2: Negative Error (Testing Arithmetic Shift)
        // (-1024 >> 2) * 256 >> 8 => -256 * 256 >> 8 = -256
        error_term = -32'd1024;
        gradient_val = 32'd256;
        #10;
        $display("Time: %t | Error: %d | Grad: %d | Delta: %d", $time, error_term, gradient_val, delta_out);

        // Test Case 3: Large Product (Testing 64-bit internal width)
        error_term = 32'd40000;
        gradient_val = 32'd20000;
        #10;
        $display("Time: %t | Error: %d | Grad: %d | Delta: %d", $time, error_term, gradient_val, delta_out);

        // Test Case 4: Disable signal (Output should not change)
        enable = 0;
        error_term = 32'd0;
        #10;
        $display("Time: %t | (Disabled) Error: %d | Delta: %d", $time, error_term, delta_out);

        #50;
        $finish;
    end

endmodule

extention/backprop_sim.vcd
$date
	Mon Feb 23 09:00:12 2026
$end
$version
	Icarus Verilog
$end
$timescale
	1ps
$end
$scope module custom_backprop_unit_tb $end
$var wire 32 ! delta_out [31:0] $end
$var reg 1 " clk $end
$var reg 1 # enable $end
$var reg 32 $ error_term [31:0] $end
$var reg 32 % gradient_val [31:0] $end
$var reg 1 & rst_n $end
$scope module uut $end
$var wire 1 " clk $end
$var wire 1 # enable $end
$var wire 32 ' error_term [31:0] $end
$var wire 32 ( gradient_val [31:0] $end
$var wire 1 & rst_n $end
$var wire 64 ) shifted_result [63:0] $end
$var wire 64 * raw_product [63:0] $end
$var wire 32 + error_scaled [31:0] $end
$var reg 32 , delta_out [31:0] $end
$upscope $end
$upscope $end
$enddefinitions $end
$comment Show the parameter values. $end
$dumpall
$end
#0
$dumpvars
b0 ,
b0 +
b0 *
b0 )
b0 (
b0 '
0&
b0 %
b0 $
0#
0"
b0 !
$end
#5000
1"
#10000
0"
#15000
1"
#20000
0"
1&
#25000
1"
#30000
b100000000 )
b10000000000000000 *
b100000000 +
0"
b100000000 %
b100000000 (
b10000000000 $
b10000000000 '
1#
#35000
b100000000 !
b100000000 ,
1"
#40000
b1111111111111111111111111111111111111111111111111111111100000000 )
b1111111111111111111111111111111111111111111111110000000000000000 *
b11111111111111111111111100000000 +
0"
b11111111111111111111110000000000 $
b11111111111111111111110000000000 '
#45000
b11111111111111111111111100000000 !
b11111111111111111111111100000000 ,
1"
#50000
b10111110101111000010 )
b10011100010000 +
0"
b1011111010111100001000000000 *
b100111000100000 %
b100111000100000 (
b1001110001000000 $
b1001110001000000 '
#55000
b10111110101111000010 !
b10111110101111000010 ,
1"
#60000
b0 )
b0 *
b0 +
0"
b0 $
b0 '
0#
