RISC_V/extention/customUnit.v
module custom_backprop_unit (
    input  wire                 clk,
    input  wire                 rst_n,
    input  wire                 enable,
    input  wire signed [15:0]   error_term,
    input  wire signed [15:0]   gradient_val,
    input  wire                 grad_valid,
    input  wire                 spike_status,
    output reg  signed [31:0]   delta_out
);

    localparam signed [15:0] BETA = 16'sd243; // 0.95 * 256

    reg  signed [31:0] dm_prev;

    wire signed [31:0] error_fixed;
    wire signed [31:0] grad_fixed;
    wire signed [63:0] beta_mul;
    wire signed [31:0] temporal_term;
    wire signed [31:0] effective_error;
    wire signed [63:0] grad_mul;
    wire signed [31:0] delta_calc;
    wire signed [31:0] delta_spike_gated;
    wire signed [31:0] dm_next_calc;

    assign error_fixed   = {{16{error_term[15]}}, error_term};
    assign grad_fixed    = {{16{gradient_val[15]}}, gradient_val};
    assign beta_mul      = $signed(dm_prev) * $signed(BETA);
    assign temporal_term = beta_mul >>> 8;
    assign effective_error = error_fixed + temporal_term;
    assign grad_mul      = $signed(effective_error) * $signed(grad_fixed);
    assign delta_calc    = grad_mul >>> 8;
    assign delta_spike_gated = spike_status ? delta_calc : 32'sd0;
    assign dm_next_calc  = spike_status ? 32'sd0 : delta_calc;

    always @(posedge clk or negedge rst_n) begin
        if (!rst_n) begin
            delta_out <= 32'sd0;
            dm_prev <= 32'sd0;
        end else if (enable && grad_valid) begin
            delta_out <= delta_spike_gated;
            dm_prev <= dm_next_calc;
        end else begin
            delta_out <= 32'sd0;
        end
    end

endmodule

RISC_V/extention/customUnit_tb.v
`timescale 1ns / 1ps

// ============================================================================
// Testbench: custom_backprop_unit
//
// Verifies the 16-bit fixed-point backpropagation unit used in the custom
// RV32IM neuromorphic extension.  All arithmetic is Q8.8 (scaled by 256).
//
// Port widths match custom_backprop_unit:
//   error_term  : signed [15:0]
//   gradient_val: signed [15:0]
//   grad_valid  : 1-bit stream-valid qualifier
//   spike_status: 1-bit temporal gate (1 = neuron fired this step)
// ============================================================================

module custom_backprop_unit_tb;

    // --- 1. Signal Declarations ---
    reg         clk;
    reg         rst_n;
    reg         enable;
    reg  signed [15:0] error_term;
    reg  signed [15:0] gradient_val;
    reg         grad_valid;
    reg         spike_status;
    wire signed [31:0] delta_out;

    integer pass_count;
    integer fail_count;

    // --- 2. Instantiate the Unit Under Test (UUT) ---
    custom_backprop_unit uut (
        .clk(clk),
        .rst_n(rst_n),
        .enable(enable),
        .error_term(error_term),
        .gradient_val(gradient_val),
        .grad_valid(grad_valid),
        .spike_status(spike_status),
        .delta_out(delta_out)
    );

    // --- 3. Clock Generation (10ns period = 100MHz) ---
    always #5 clk = ~clk;

    // --- 4. Check task ---
    task check;
        input signed [31:0] expected;
        input [127:0] label;
        begin
            if ($signed(delta_out) === expected) begin
                $display("[PASS] %s | delta_out=%0d", label, $signed(delta_out));
                pass_count = pass_count + 1;
            end else begin
                $display("[FAIL] %s | delta_out=%0d  expected=%0d",
                         label, $signed(delta_out), expected);
                fail_count = fail_count + 1;
            end
        end
    endtask

    // --- 5. Stimulus Block ---
    initial begin
        // Initialise
        clk          = 0;
        rst_n        = 0;
        enable       = 0;
        grad_valid   = 0;
        spike_status = 0;
        error_term   = 0;
        gradient_val = 0;
        pass_count   = 0;
        fail_count   = 0;

        $dumpfile("backprop_sim.vcd");
        $dumpvars(0, custom_backprop_unit_tb);

        // Reset sequence
        #20 rst_n = 1;
        #10 enable = 1;

        // ----------------------------------------------------------------
        // TC1: spike_status=1, positive values — basic spike-gated delta
        //   dm_prev=0, error=100, grad=128
        //   effective_error = 100 + 0 = 100
        //   delta_calc = (100 * 128) >>> 8 = 12800 >>> 8 = 50
        //   delta_spike_gated = 50  (spike=1)
        //   dm_next = 0             (spike=1 resets dm)
        // ----------------------------------------------------------------
        error_term   = 16'sd100;
        gradient_val = 16'sd128;
        grad_valid   = 1'b1;
        spike_status = 1'b1;
        #10;
        check(32'sd50, "TC1 spike=1  error= 100 grad=128");

        // ----------------------------------------------------------------
        // TC2: spike_status=0 — no spike, temporal delta accumulates
        //   dm_prev=0 (TC1 spike reset it), error=200, grad=64
        //   delta_calc = (200 * 64) >>> 8 = 12800 >>> 8 = 50
        //   delta_spike_gated = 0   (no spike)
        //   dm_next = 50
        // ----------------------------------------------------------------
        error_term   = 16'sd200;
        gradient_val = 16'sd64;
        spike_status = 1'b0;
        #10;
        check(32'sd0,  "TC2 spike=0  error= 200 grad= 64");

        // ----------------------------------------------------------------
        // TC3: spike_status=1 with temporal momentum from TC2
        //   dm_prev=50, error=50, grad=64, BETA=192 (0.75*256)
        //   beta_mul = 50 * 192 = 9600
        //   temporal_term = 9600 >>> 8 = 37
        //   effective_error = 50 + 37 = 87
        //   delta_calc = (87 * 64) >>> 8 = 5568 >>> 8 = 21
        //   delta_spike_gated = 21 (spike=1)
        //   dm_next = 0
        // ----------------------------------------------------------------
        error_term   = 16'sd50;
        gradient_val = 16'sd64;
        spike_status = 1'b1;
        #10;
        check(32'sd21, "TC3 spike=1  error=  50 grad= 64 (with temporal)");

        // ----------------------------------------------------------------
        // TC4: negative gradient (signed arithmetic), spike active
        //   dm_prev=0 (TC3 spike reset it), error=-100, grad=128
        //   delta_calc = (-100 * 128) >>> 8 = -12800 >>> 8 = -50
        //   delta_spike_gated = -50 (spike=1)
        // ----------------------------------------------------------------
        error_term   = -16'sd100;
        gradient_val = 16'sd128;
        spike_status = 1'b1;
        #10;
        check(-32'sd50, "TC4 spike=1  error=-100 grad=128 (neg grad)");

        // ----------------------------------------------------------------
        // TC5: grad_valid deasserted — output must clear to 0
        // ----------------------------------------------------------------
        grad_valid = 1'b0;
        #10;
        check(32'sd0,  "TC5 grad_valid=0 (output must be 0)");

        // Summary
        $display("----------------------------------------");
        $display("Results: %0d PASS, %0d FAIL", pass_count, fail_count);
        if (fail_count == 0)
            $display("[PASS] All custom_backprop_unit tests passed.");
        else
            $display("[FAIL] %0d test(s) failed.", fail_count);

        #50;
        $finish;
    end

endmodule

RISC_V/extention/backprop_sim.vcd
$date
	Sat Mar 14 21:24:28 2026
$end
$version
	Icarus Verilog
$end
$timescale
	1ps
$end
$scope module custom_backprop_unit_tb $end
$var wire 32 ! delta_out [31:0] $end
$var reg 1 " clk $end
$var reg 1 # enable $end
$var reg 16 $ error_term [15:0] $end
$var reg 1 % grad_valid $end
$var reg 16 & gradient_val [15:0] $end
$var reg 1 ' rst_n $end
$var reg 1 ( spike_status $end
$var integer 32 ) fail_count [31:0] $end
$var integer 32 * pass_count [31:0] $end
$scope module uut $end
$var wire 1 " clk $end
$var wire 1 # enable $end
$var wire 16 + error_term [15:0] $end
$var wire 1 % grad_valid $end
$var wire 16 , gradient_val [15:0] $end
$var wire 1 ' rst_n $end
$var wire 1 ( spike_status $end
$var wire 32 - temporal_term [31:0] $end
$var wire 64 . grad_mul [63:0] $end
$var wire 32 / grad_fixed [31:0] $end
$var wire 32 0 error_fixed [31:0] $end
$var wire 32 1 effective_error [31:0] $end
$var wire 32 2 dm_next_calc [31:0] $end
$var wire 32 3 delta_spike_gated [31:0] $end
$var wire 32 4 delta_calc [31:0] $end
$var wire 64 5 beta_mul [63:0] $end
$var parameter 16 6 BETA $end
$var reg 32 7 delta_out [31:0] $end
$var reg 32 8 dm_prev [31:0] $end
$upscope $end
$scope task check $end
$var reg 32 9 expected [31:0] $end
$var reg 128 : label [127:0] $end
$upscope $end
$upscope $end
$enddefinitions $end
$comment Show the parameter values. $end
$dumpall
b11000000 6
$end
#0
$dumpvars
bx :
bx 9
b0 8
b0 7
b0 5
b0 4
b0 3
b0 2
b0 1
b0 0
b0 /
b0 .
b0 -
b0 ,
b0 +
b0 *
b0 )
0(
0'
b0 &
0%
b0 $
0#
0"
b0 !
$end
#5000
1"
#10000
0"
#15000
1"
#20000
0"
1'
#25000
1"
#30000
b110010 3
b110010 4
0"
1(
1%
b11001000000000 .
b10000000 /
b10000000 &
b10000000 ,
b1100100 1
b1100100 0
b1100100 $
b1100100 +
1#
#35000
b110010 !
b110010 7
1"
#40000
b0 3
b110010 2
0"
0(
b1000000 /
b1000000 &
b1000000 ,
b11001000000000 .
b11001000 1
b11001000 0
b11001000 $
b11001000 +
b1 *
b1101111011100100011110100100000001100010011000000110000001000000110011101110010011000010110010000111101001100010011001000111000 :
b110010 9
#45000
b111011 2
b111011 4
b11101101000000 .
b11101101 1
b100101 -
b10010110000000 5
b110010 8
b0 !
b0 7
1"
#50000
b10101 4
b10101 3
b0 2
0"
1(
b1010111000000 .
b1010111 1
b110010 0
b110010 $
b110010 +
b10 *
b1101111011100100011110100100000001100100011000000110000001000000110011101110010011000010110010000111101001000000011011000110100 :
b0 9
#55000
b1100 3
b1100 4
b110010000000 .
b110010 1
b0 -
b0 5
b0 8
b10101 !
b10101 7
1"
#60000
b11111111111111111111111111001110 3
b11111111111111111111111111001110 4
0"
b10000000 /
b10000000 &
b10000000 ,
b1111111111111111111111111111111111111111111111111100111000000000 .
b11111111111111111111111110011100 1
b11111111111111111111111110011100 0
b1111111110011100 $
b1111111110011100 +
b11 *
b100000001010000111011101101001011101000110100000100000011101000110010101101101011100000110111101110010011000010110110000101001 :
b10101 9
#65000
b11111111111111111111111111001110 !
b11111111111111111111111111001110 7
1"
#70000
0"
0%
b100 *
b1100100001111010011000100110010001110000010000000101000011011100110010101100111001000000110011101110010011000010110010000101001 :
b11111111111111111111111111001110 9
#75000
b0 !
b0 7
1"
#80000
0"
b101 *
b1110101011101000111000001110101011101000010000001101101011101010111001101110100001000000110001001100101001000000011000000101001 :
b0 9
