RISC_V/extention/customUnit.v
  module custom_backprop_unit (
    input  wire                 clk,          // System Clock
    input  wire                 rst_n,        // Active-low Reset
    input  wire                 enable,       // Optional: Only update when instruction is valid
    
    // Inputs from Register File / Memory
    input  wire signed [31:0]   error_term,   // Input 1 (Calculated Error)
    input  wire signed [31:0]   gradient_val, // Input 2 (From Surrogate RAM)

    // Output to Pipeline/ALU
    output reg  signed [31:0]   delta_out     // The calculated gradient change
);

    // --- 1. Internal Signals (Combinational Math) ---
    wire signed [31:0] error_scaled;
    wire signed [63:0] raw_product;
    wire signed [63:0] shifted_result;

    // --- 2. Step A: Pre-Scaling (Matches your Diagram bubble "(Error_term)>>2") ---
    // We use arithmetic shift (>>>) to preserve the sign of the error.
    assign error_scaled = error_term >>> 2;

    // --- 3. Step B: Multiplication (Matches "Multiplier" box) ---
    // 32-bit * 32-bit = 64-bit result to prevent overflow.
    assign raw_product = error_scaled * gradient_val;

    // --- 4. Step C: Post-Scaling (Matches "Shift Right 8" box) ---
    // Fixed-point adjustment (division by 256).
    assign shifted_result = raw_product >>> 8;

    // --- 5. Step D: Pipeline Register ---
    // This holds the value for the NEXT clock cycle, allowing the 
    // Weight Update (Addition) to happen in cycle 2.
    always @(shifted_result) begin   
        if (!rst_n) begin
            delta_out <= 32'd0;
        end else if (enable) begin
            // Truncate back to 32 bits and store in the register
            delta_out <= shifted_result[31:0];
        end
    end    

endmodule

RISC_V/extention/Adder_extension.v
`include "customUnit.v"

module customCalculation (clk, rst_n, enable, error_term, gradient_val, weight, load_new_weight, Updated_weight);
    input wire signed [31:0] error_term;   // Input 1 (Calculated Error)
    input wire signed [31:0] gradient_val; // Input 2 (From Surrogate RAM)
    input wire clk, rst_n, enable; // Control signals for the pipeline register
    input wire signed [31:0] weight; // Current weight value for addition in cycle 2
    input wire load_new_weight; // Signal to load new weight value
    output reg signed [31:0] Updated_weight;   // The calculated weight change

    wire signed [31:0] delta_out;
    reg signed [31:0] delta_out_buffer;;
    reg [2:0] data_valid;

    custom_backprop_unit backprop_unit (
        .clk(clk),
        .rst_n(rst_n),
        .enable(enable),
        .error_term(error_term),
        .gradient_val(gradient_val),
        .delta_out(delta_out)
    );

    always @(posedge clk or negedge rst_n) begin
        delta_out_buffer <= delta_out;
        data_valid <=data_valid + 2'b01;
    end

    always @(posedge clk or negedge rst_n) begin
        if (!rst_n) begin
            Updated_weight <= 0;
            data_valid   <= 1'b0;
        end else if (enable) begin
            if(load_new_weight) begin
                Updated_weight <= weight;
            end 
            else if (data_valid>=2) begin
                Updated_weight <= Updated_weight + delta_out_buffer; // Update weight with the calculated delta           
            end 
            
        end
    end
endmodule

RISC_V/extention/Adder_extension_tb.v
`timescale 1ns / 1ps

module customCalculation_tb;
    reg clk, rst_n, enable,load_new_weight;
    reg signed [31:0] error_term, gradient_val, weight;
    wire signed [31:0] Updated_weight;

    customCalculation uut (
        .clk(clk), .rst_n(rst_n), .enable(enable),
        .error_term(error_term), .gradient_val(gradient_val),
        .weight(weight), .load_new_weight(load_new_weight), .Updated_weight(Updated_weight)
    );

    always #5 clk = ~clk;


    initial begin
        $dumpfile("pipeline_sim.vcd");
        $dumpvars(0, customCalculation_tb);

        clk = 0; rst_n = 0; enable = 1; load_new_weight = 0;
        weight = 1000;
        
        #10 rst_n = 1;
        load_new_weight = 1;  // Load initial weight value
        enable =1;
        #10;
        load_new_weight = 0;  // Start calculations
        // Feed data continuously to test the pipeline
        error_term = 1024;  gradient_val = 256; #10; // Delta: 256
        error_term = 2048;  gradient_val = 256; #10; // Delta: 512
        error_term = 4096;  gradient_val = 256; #10; // Delta: 1024
        
        #20 $finish;
    end
endmodule

RISC_V/extention/pipeline_sim.vcd
$date
	Thu Mar 05 04:25:55 2026
$end
$version
	Icarus Verilog
$end
$timescale
	1ps
$end
$scope module customCalculation_tb $end
$var wire 32 ! Updated_weight [31:0] $end
$var reg 1 " clk $end
$var reg 1 # enable $end
$var reg 32 $ error_term [31:0] $end
$var reg 32 % gradient_val [31:0] $end
$var reg 1 & load_new_weight $end
$var reg 1 ' rst_n $end
$var reg 32 ( weight [31:0] $end
$scope module uut $end
$var wire 1 " clk $end
$var wire 1 # enable $end
$var wire 32 ) error_term [31:0] $end
$var wire 32 * gradient_val [31:0] $end
$var wire 1 & load_new_weight $end
$var wire 1 ' rst_n $end
$var wire 32 + weight [31:0] $end
$var wire 32 , delta_out [31:0] $end
$var reg 32 - Updated_weight [31:0] $end
$var reg 3 . data_valid [2:0] $end
$var reg 32 / delta_out_buffer [31:0] $end
$scope module backprop_unit $end
$var wire 1 " clk $end
$var wire 1 # enable $end
$var wire 32 0 error_term [31:0] $end
$var wire 32 1 gradient_val [31:0] $end
$var wire 1 ' rst_n $end
$var wire 64 2 shifted_result [63:0] $end
$var wire 64 3 raw_product [63:0] $end
$var wire 32 4 error_scaled [31:0] $end
$var reg 32 5 delta_out [31:0] $end
$upscope $end
$upscope $end
$upscope $end
$enddefinitions $end
$comment Show the parameter values. $end
$dumpall
$end
#0
$dumpvars
bx 5
bx 4
bx 3
bx 2
bx 1
bx 0
bx /
bx .
b0 -
bx ,
b1111101000 +
bx *
bx )
b1111101000 (
0'
0&
bx %
bx $
1#
0"
b0 !
$end
#5000
b0 .
1"
#10000
0"
1&
1'
#15000
b1 .
b1111101000 !
b1111101000 -
1"
#20000
b100000000 ,
b100000000 5
b100000000 2
b10000000000000000 3
b100000000 4
0"
b100000000 %
b100000000 *
b100000000 1
b10000000000 $
b10000000000 )
b10000000000 0
0&
#25000
b10 .
b100000000 /
1"
#30000
b1000000000 ,
b1000000000 5
b1000000000 2
b100000000000000000 3
b1000000000 4
0"
b100000000000 $
b100000000000 )
b100000000000 0
#35000
b11 .
b1000000000 /
b10011101000 !
b10011101000 -
1"
#40000
b10000000000 ,
b10000000000 5
b10000000000 2
b1000000000000000000 3
b10000000000 4
0"
b1000000000000 $
b1000000000000 )
b1000000000000 0
#45000
b11011101000 !
b11011101000 -
b100 .
b10000000000 /
1"
#50000
0"
#55000
b101 .
b101011101000 !
b101011101000 -
1"
#60000
0"
#65000
b111011101000 !
b111011101000 -
b110 .
1"
